aiojobs/__init__.py
aiojobs/_job.py
aiojobs/_scheduler.py
aiojobs/aiohttp.py
aiojobs/py.typed
aiojobs-1.3.0.dist-info/LICENSE
aiojobs-1.3.0.dist-info/METADATA
aiojobs-1.3.0.dist-info/WHEEL
aiojobs-1.3.0.dist-info/top_level.txt
aiojobs-1.3.0.dist-info/RECORD
