Metadata-Version: 2.1
Name: aiojobs
Version: 1.3.0
Summary: Job scheduler for managing background tasks (asyncio)
Home-page: https://github.com/aio-libs/aiojobs
Maintainer: aiohttp team <team@aiohttp.org>
Maintainer-email: team@aiohttp.org
License: Apache 2
Project-URL: Chat: Gitter, https://gitter.im/aio-libs/Lobby
Project-URL: CI: GitHub Actions, https://github.com/aio-libs/aiojobs/actions?query=workflow%3ACI
Project-URL: Coverage: codecov, https://codecov.io/github/aio-libs/aiojobs
Project-URL: Docs: Changelog, https://aiojobs.readthedocs.io/en/stable/changes.html
Project-URL: Docs: RTD, https://aiojobs.readthedocs.io/en/stable/
Project-URL: GitHub: issues, https://github.com/aio-libs/aiojobs/issues
Project-URL: GitHub: repo, https://github.com/aio-libs/aiojobs
Classifier: Development Status :: 5 - Production/Stable
Classifier: Framework :: AsyncIO
Classifier: Intended Audience :: Developers
Classifier: License :: OSI Approved :: Apache Software License
Classifier: Operating System :: POSIX
Classifier: Operating System :: MacOS :: MacOS X
Classifier: Operating System :: Microsoft :: Windows
Classifier: Programming Language :: Python
Classifier: Programming Language :: Python :: 3
Classifier: Programming Language :: Python :: 3.8
Classifier: Programming Language :: Python :: 3.9
Classifier: Programming Language :: Python :: 3.10
Classifier: Programming Language :: Python :: 3.11
Classifier: Programming Language :: Python :: 3.12
Classifier: Topic :: Software Development
Requires-Python: >=3.8
License-File: LICENSE
Requires-Dist: async-timeout>=4.0.0; python_version < "3.11"
Provides-Extra: aiohttp
Requires-Dist: aiohttp>=3.9.0; extra == "aiohttp"
